{
  "generatedAt": "2026-04-11T06:18:39.847Z",
  "seed": "20260410",
  "chapters": [
    "CH06",
    "CH07",
    "CH08",
    "CH09",
    "CH10"
  ],
  "players": [
    {
      "playerId": "player-01",
      "strategy": "cautious",
      "chapterResults": [
        {
          "chapterId": "CH06",
          "status": "success",
          "reason": "END_CH06_RESOLVED",
          "steps": 10,
          "choicesTaken": 10,
          "eventsVisited": 10,
          "endHp": 68,
          "endNoise": 17,
          "rawEstimatedMinutes": 40,
          "estimatedMinutes": 5.2,
          "startHp": 100,
          "startNoise": 0,
          "startContamination": 0,
          "endContamination": 10,
          "loopCount": 0,
          "repeatFarmEvents": {},
          "routeChoiceCount": 1,
          "majorChoices": [
            {
              "choiceId": "ch06_entry_slow",
              "count": 1
            },
            {
              "choiceId": "ch06_route_official",
              "count": 1
            },
            {
              "choiceId": "ch06_approach_record",
              "count": 1
            }
          ],
          "endingId": null,
          "review": "Chapter pacing stayed readable, but branch identity can still sharpen. Cautious routing changed noise by +17 and contamination by +10. The route stayed close to linear progression without farm loops. set_route was applied 1 time(s). Major choices: ch06_entry_slow(1), ch06_route_official(1). Playtime target (5m) met. Finished with END_CH06_RESOLVED. No major warnings.",
          "warnings": [],
          "preChapterItems": {
            "itm_delivery_badge": 0,
            "itm_security_badge": 0,
            "itm_route_clearance_pangyo": 0
          }
        },
        {
          "chapterId": "CH07",
          "status": "success",
          "reason": "END_CH07_RESOLVED",
          "steps": 12,
          "choicesTaken": 12,
          "eventsVisited": 12,
          "endHp": 58,
          "endNoise": 24,
          "rawEstimatedMinutes": 48,
          "estimatedMinutes": 6.4,
          "startHp": 86,
          "startNoise": 7,
          "startContamination": 6,
          "endContamination": 16,
          "loopCount": 0,
          "repeatFarmEvents": {},
          "routeChoiceCount": 1,
          "majorChoices": [
            {
              "choiceId": "ch07_entry_slow",
              "count": 1
            },
            {
              "choiceId": "ch07_route_witness",
              "count": 1
            },
            {
              "choiceId": "ch07_approach_record",
              "count": 1
            }
          ],
          "endingId": null,
          "review": "Chapter pacing stayed readable, but branch identity can still sharpen. Cautious routing changed noise by +17 and contamination by +10. The route stayed close to linear progression without farm loops. set_route was applied 1 time(s). Major choices: ch07_entry_slow(1), ch07_route_witness(1). Playtime target (6m) met. Finished with END_CH07_RESOLVED. No major warnings.",
          "warnings": [],
          "preChapterItems": {
            "itm_delivery_badge": 1,
            "itm_security_badge": 0,
            "itm_route_clearance_pangyo": 0
          }
        },
        {
          "chapterId": "CH08",
          "status": "success",
          "reason": "END_CH08_RESOLVED",
          "steps": 10,
          "choicesTaken": 10,
          "eventsVisited": 10,
          "endHp": 42,
          "endNoise": 32,
          "rawEstimatedMinutes": 40,
          "estimatedMinutes": 6.2,
          "startHp": 76,
          "startNoise": 14,
          "startContamination": 12,
          "endContamination": 23,
          "loopCount": 0,
          "repeatFarmEvents": {},
          "routeChoiceCount": 1,
          "majorChoices": [
            {
              "choiceId": "ch08_entry_slow",
              "count": 1
            },
            {
              "choiceId": "ch08_route_official",
              "count": 1
            },
            {
              "choiceId": "ch08_approach_record",
              "count": 1
            }
          ],
          "endingId": null,
          "review": "Chapter pacing stayed readable, but branch identity can still sharpen. Cautious routing changed noise by +18 and contamination by +11. The route stayed close to linear progression without farm loops. set_route was applied 1 time(s). Major choices: ch08_entry_slow(1), ch08_route_official(1). Playtime target (6m) met. Finished with END_CH08_RESOLVED. No major warnings.",
          "warnings": [],
          "preChapterItems": {
            "itm_delivery_badge": 1,
            "itm_security_badge": 1,
            "itm_route_clearance_pangyo": 0
          }
        },
        {
          "chapterId": "CH09",
          "status": "success",
          "reason": "END_CH09_RESOLVED",
          "steps": 10,
          "choicesTaken": 10,
          "eventsVisited": 10,
          "endHp": 35,
          "endNoise": 40,
          "rawEstimatedMinutes": 40,
          "estimatedMinutes": 6.2,
          "startHp": 63,
          "startNoise": 22,
          "startContamination": 19,
          "endContamination": 30,
          "loopCount": 0,
          "repeatFarmEvents": {},
          "routeChoiceCount": 1,
          "majorChoices": [
            {
              "choiceId": "ch09_entry_slow",
              "count": 1
            },
            {
              "choiceId": "ch09_route_broker",
              "count": 1
            },
            {
              "choiceId": "ch09_approach_record",
              "count": 1
            }
          ],
          "endingId": null,
          "review": "Chapter pacing stayed readable, but branch identity can still sharpen. Cautious routing changed noise by +18 and contamination by +11. The route stayed close to linear progression without farm loops. set_route was applied 1 time(s). Major choices: ch09_entry_slow(1), ch09_route_broker(1). Playtime target (6m) met. Finished with END_CH09_RESOLVED. No major warnings.",
          "warnings": [],
          "preChapterItems": {
            "itm_delivery_badge": 1,
            "itm_security_badge": 2,
            "itm_route_clearance_pangyo": 0
          }
        },
        {
          "chapterId": "CH10",
          "status": "success",
          "reason": "END_CH10_RESOLVED",
          "steps": 12,
          "choicesTaken": 12,
          "eventsVisited": 12,
          "endHp": 25,
          "endNoise": 50,
          "rawEstimatedMinutes": 48,
          "estimatedMinutes": 7.4,
          "startHp": 63,
          "startNoise": 30,
          "startContamination": 26,
          "endContamination": 35,
          "loopCount": 0,
          "repeatFarmEvents": {},
          "routeChoiceCount": 1,
          "majorChoices": [
            {
              "choiceId": "ch10_entry_slow",
              "count": 1
            },
            {
              "choiceId": "ch10_route_broker",
              "count": 1
            },
            {
              "choiceId": "ch10_approach_record",
              "count": 1
            }
          ],
          "endingId": "P2_END_RED_CORRIDOR",
          "review": "Chapter pacing stayed readable, but branch identity can still sharpen. Cautious routing changed noise by +20 and contamination by +9. The route stayed close to linear progression without farm loops. set_route was applied 1 time(s). Major choices: ch10_entry_slow(1), ch10_route_broker(1). Playtime target (7m) met. Finished with END_CH10_RESOLVED. No major warnings.",
          "warnings": [],
          "preChapterItems": {
            "itm_delivery_badge": 1,
            "itm_security_badge": 3,
            "itm_route_clearance_pangyo": 0
          }
        }
      ],
      "finalStats": {
        "hp": 63,
        "maxHp": 100,
        "noise": 40,
        "contamination": 31,
        "playMinutes": 216,
        "inventoryItemCount": 8,
        "inventorySample": {
          "itm_backpack_salvage_10": 2,
          "itm_battery_pack": 4,
          "itm_box_label_roll": 7,
          "itm_container_seal": 15,
          "itm_delivery_badge": 2,
          "itm_disinfectant": 4,
          "itm_med_crate_tag": 7,
          "itm_security_badge": 3
        },
        "chapterMinutes": {
          "CH06": 40,
          "CH07": 48,
          "CH08": 40,
          "CH09": 40,
          "CH10": 48
        }
      },
      "warnings": [],
      "overallSummary": {
        "status": "success",
        "clearedChapters": [
          "CH06",
          "CH07",
          "CH08",
          "CH09",
          "CH10"
        ],
        "failedChapter": null,
        "totalSteps": 54,
        "totalChoices": 54,
        "totalEstimatedMinutes": 31.4
      }
    },
    {
      "playerId": "player-02",
      "strategy": "aggressive",
      "chapterResults": [
        {
          "chapterId": "CH06",
          "status": "success",
          "reason": "END_CH06_RESOLVED",
          "steps": 10,
          "choicesTaken": 10,
          "eventsVisited": 10,
          "endHp": 68,
          "endNoise": 19,
          "rawEstimatedMinutes": 40,
          "estimatedMinutes": 5.2,
          "startHp": 100,
          "startNoise": 0,
          "startContamination": 0,
          "endContamination": 10,
          "loopCount": 0,
          "repeatFarmEvents": {},
          "routeChoiceCount": 1,
          "majorChoices": [
            {
              "choiceId": "ch06_entry_slow",
              "count": 1
            },
            {
              "choiceId": "ch06_route_broker",
              "count": 1
            },
            {
              "choiceId": "ch06_approach_record",
              "count": 1
            }
          ],
          "endingId": null,
          "review": "Chapter pacing stayed readable, but branch identity can still sharpen. Aggressive routing changed noise by +19 and hp by -32. The route stayed close to linear progression without farm loops. set_route was applied 1 time(s). Major choices: ch06_entry_slow(1), ch06_route_broker(1). Playtime target (5m) met. Finished with END_CH06_RESOLVED. No major warnings.",
          "warnings": [],
          "preChapterItems": {
            "itm_delivery_badge": 0,
            "itm_security_badge": 0,
            "itm_route_clearance_pangyo": 0
          }
        },
        {
          "chapterId": "CH07",
          "status": "success",
          "reason": "END_CH07_RESOLVED",
          "steps": 10,
          "choicesTaken": 10,
          "eventsVisited": 10,
          "endHp": 58,
          "endNoise": 27,
          "rawEstimatedMinutes": 40,
          "estimatedMinutes": 6.2,
          "startHp": 86,
          "startNoise": 9,
          "startContamination": 6,
          "endContamination": 14,
          "loopCount": 0,
          "repeatFarmEvents": {},
          "routeChoiceCount": 1,
          "majorChoices": [
            {
              "choiceId": "ch07_entry_slow",
              "count": 1
            },
            {
              "choiceId": "ch07_route_broker",
              "count": 1
            },
            {
              "choiceId": "ch07_approach_record",
              "count": 1
            }
          ],
          "endingId": null,
          "review": "Chapter pacing stayed readable, but branch identity can still sharpen. Aggressive routing changed noise by +18 and hp by -28. The route stayed close to linear progression without farm loops. set_route was applied 1 time(s). Major choices: ch07_entry_slow(1), ch07_route_broker(1). Playtime target (6m) met. Finished with END_CH07_RESOLVED. No major warnings.",
          "warnings": [],
          "preChapterItems": {
            "itm_delivery_badge": 1,
            "itm_security_badge": 0,
            "itm_route_clearance_pangyo": 0
          }
        },
        {
          "chapterId": "CH08",
          "status": "success",
          "reason": "END_CH08_RESOLVED",
          "steps": 12,
          "choicesTaken": 12,
          "eventsVisited": 12,
          "endHp": 42,
          "endNoise": 38,
          "rawEstimatedMinutes": 48,
          "estimatedMinutes": 6.4,
          "startHp": 76,
          "startNoise": 17,
          "startContamination": 10,
          "endContamination": 21,
          "loopCount": 0,
          "repeatFarmEvents": {},
          "routeChoiceCount": 1,
          "majorChoices": [
            {
              "choiceId": "ch08_entry_slow",
              "count": 1
            },
            {
              "choiceId": "ch08_route_witness",
              "count": 1
            },
            {
              "choiceId": "ch08_approach_record",
              "count": 1
            }
          ],
          "endingId": null,
          "review": "Chapter pacing stayed readable, but branch identity can still sharpen. Aggressive routing changed noise by +21 and hp by -34. The route stayed close to linear progression without farm loops. set_route was applied 1 time(s). Major choices: ch08_entry_slow(1), ch08_route_witness(1). Playtime target (6m) met. Finished with END_CH08_RESOLVED. No major warnings.",
          "warnings": [],
          "preChapterItems": {
            "itm_delivery_badge": 1,
            "itm_security_badge": 0,
            "itm_route_clearance_pangyo": 0
          }
        },
        {
          "chapterId": "CH09",
          "status": "success",
          "reason": "END_CH09_RESOLVED",
          "steps": 12,
          "choicesTaken": 12,
          "eventsVisited": 12,
          "endHp": 35,
          "endNoise": 49,
          "rawEstimatedMinutes": 48,
          "estimatedMinutes": 6.4,
          "startHp": 63,
          "startNoise": 28,
          "startContamination": 17,
          "endContamination": 28,
          "loopCount": 0,
          "repeatFarmEvents": {},
          "routeChoiceCount": 1,
          "majorChoices": [
            {
              "choiceId": "ch09_entry_slow",
              "count": 1
            },
            {
              "choiceId": "ch09_route_broker",
              "count": 1
            },
            {
              "choiceId": "ch09_approach_record",
              "count": 1
            }
          ],
          "endingId": null,
          "review": "Chapter pacing stayed readable, but branch identity can still sharpen. Aggressive routing changed noise by +21 and hp by -28. The route stayed close to linear progression without farm loops. set_route was applied 1 time(s). Major choices: ch09_entry_slow(1), ch09_route_broker(1). Playtime target (6m) met. Finished with END_CH09_RESOLVED. No major warnings.",
          "warnings": [],
          "preChapterItems": {
            "itm_delivery_badge": 1,
            "itm_security_badge": 1,
            "itm_route_clearance_pangyo": 0
          }
        },
        {
          "chapterId": "CH10",
          "status": "success",
          "reason": "END_CH10_RESOLVED",
          "steps": 10,
          "choicesTaken": 10,
          "eventsVisited": 10,
          "endHp": 25,
          "endNoise": 60,
          "rawEstimatedMinutes": 40,
          "estimatedMinutes": 7.2,
          "startHp": 63,
          "startNoise": 39,
          "startContamination": 24,
          "endContamination": 35,
          "loopCount": 0,
          "repeatFarmEvents": {},
          "routeChoiceCount": 1,
          "majorChoices": [
            {
              "choiceId": "ch10_entry_slow",
              "count": 1
            },
            {
              "choiceId": "ch10_route_witness",
              "count": 1
            },
            {
              "choiceId": "ch10_approach_record",
              "count": 1
            }
          ],
          "endingId": "P2_END_CONTROLLED_CONVOY",
          "review": "Chapter pacing stayed readable, but branch identity can still sharpen. Aggressive routing changed noise by +21 and hp by -38. The route stayed close to linear progression without farm loops. set_route was applied 1 time(s). Major choices: ch10_entry_slow(1), ch10_route_witness(1). Playtime target (7m) met. Finished with END_CH10_RESOLVED. No major warnings.",
          "warnings": [],
          "preChapterItems": {
            "itm_delivery_badge": 1,
            "itm_security_badge": 3,
            "itm_route_clearance_pangyo": 0
          }
        }
      ],
      "finalStats": {
        "hp": 63,
        "maxHp": 100,
        "noise": 50,
        "contamination": 31,
        "playMinutes": 216,
        "inventoryItemCount": 9,
        "inventorySample": {
          "itm_backpack_salvage_10": 1,
          "itm_battery_pack": 6,
          "itm_box_label_roll": 9,
          "itm_container_seal": 9,
          "itm_delivery_badge": 1,
          "itm_disinfectant": 1,
          "itm_logistics_vest": 2,
          "itm_med_crate_tag": 6,
          "itm_security_badge": 3
        },
        "chapterMinutes": {
          "CH06": 40,
          "CH07": 40,
          "CH08": 48,
          "CH09": 48,
          "CH10": 40
        }
      },
      "warnings": [],
      "overallSummary": {
        "status": "success",
        "clearedChapters": [
          "CH06",
          "CH07",
          "CH08",
          "CH09",
          "CH10"
        ],
        "failedChapter": null,
        "totalSteps": 54,
        "totalChoices": 54,
        "totalEstimatedMinutes": 31.4
      }
    }
  ],
  "overallSummary": {
    "totalPlayers": 2,
    "succeededPlayers": 2,
    "failedPlayers": 0,
    "chapterClearCounts": {
      "CH06": 2,
      "CH07": 2,
      "CH08": 2,
      "CH09": 2,
      "CH10": 2
    },
    "chapterReachedCounts": {
      "CH06": 2,
      "CH07": 2,
      "CH08": 2,
      "CH09": 2,
      "CH10": 2
    },
    "chapterEstimatedMinutes": {
      "CH06": 10.4,
      "CH07": 12.600000000000001,
      "CH08": 12.600000000000001,
      "CH09": 12.600000000000001,
      "CH10": 14.600000000000001
    },
    "averageEstimatedMinutesByChapter": {
      "CH06": 5.2,
      "CH07": 6.3,
      "CH08": 6.3,
      "CH09": 6.3,
      "CH10": 7.3
    },
    "warningCount": 0
  }
}
